branchlog.py
setup.py
hg_branchlog.egg-info/PKG-INFO
hg_branchlog.egg-info/SOURCES.txt
hg_branchlog.egg-info/dependency_links.txt
hg_branchlog.egg-info/not-zip-safe
hg_branchlog.egg-info/requires.txt
hg_branchlog.egg-info/top_level.txt